yaml_config_parser/__init__.py
yaml_config_parser/yaml_config_parser.py
yaml_config_parser-1.0.4.dist-info/METADATA
yaml_config_parser-1.0.4.dist-info/RECORD
yaml_config_parser-1.0.4.dist-info/WHEEL
yaml_config_parser-1.0.4.dist-info/entry_points.txt
yaml_config_parser-1.0.4.dist-info/top_level.txt
