Metadata-Version: 2.1
Name: yaml-config-parser
Version: 1.0.4
Summary: A simple yaml config parser tool
Home-page: https://github.com/luserv/yaml-config-parser
Author: luserv
Author-email: vasterlu@gmail.com
License: MIT
Keywords: yaml config parser
Platform: UNKNOWN
Requires-Dist: pyyaml
